imgMS/MSData.py
imgMS/MSEval.py
imgMS/MSStats.py
imgMS/__init__.py
imgMS/side_functions.py
imgMS-0.2.12.dist-info/LICENSE
imgMS-0.2.12.dist-info/METADATA
imgMS-0.2.12.dist-info/WHEEL
imgMS-0.2.12.dist-info/top_level.txt
imgMS-0.2.12.dist-info/RECORD
