Metadata-Version: 2.1
Name: imgMS
Version: 0.2.12
Summary: Package for data reduction of LA-ICP-MS data.
Home-page: https://github.com/nikadilli/imgMS
Author: nikadilli
Author-email: nikadilli@gmail.com
License: LICENSE.txt
Platform: UNKNOWN
Classifier: Programming Language :: Python :: 3
Classifier: License :: OSI Approved :: MIT License
Classifier: Operating System :: OS Independent
Requires-Python: >=3.6
Requires-Dist: matplotlib
Requires-Dist: pandas
Requires-Dist: numpy
Requires-Dist: patsy
Requires-Dist: Pillow
Requires-Dist: scikit-learn
Requires-Dist: scipy
Requires-Dist: statsmodels
Requires-Dist: xlrd
Requires-Dist: XlsxWriter
